[
    {
        "lowestResellPrice": {
            "stockX": 158,
            "flightClub": 165,
            "goat": 165
        },
        "imageLinks": [],
        "_id": "63d09e90638bbe2c6be73cba",
        "shoeName": "Jordan 1 Retro High OG True Blue",
        "brand": "Jordan",
        "silhoutte": "Jordan 1 Retro High OG",
        "styleID": "DZ5485-410",
        "make": "Jordan 1 Retro High OG",
        "colorway": "True Blue/White/Cement Grey",
        "retailPrice": 180,
        "thumbnail": "https://images.stockx.com/images/Air-Jordan-1-Retro-High-OG-True-Blue-Product.jpg?fit=fill&bg=FFFFFF&w=700&h=500&fm=webp&auto=compress&trim=color&q=90&dpr=2&updated_at=1674026406",
        "releaseDate": "2023-01-14",
        "description": "Recalling an original Air Jordan 3, the Air Jordan 1 Retro High OG 'True Blue' provides a reinterpretation of a familiar 'colorway'. True Blue on the eyestay and forefoot overlay are color-matched by the signature Swoosh, while the heel and collar overlay appear in Cement Grey with a Wings logo on the latter. Additional retro branding appears via the tongue tag with 'Nike Air.' Underfoot, comfort on and off the court is afforded by a traditional rubber cupsole with an Air-sole unit in the heel.",
        "urlKey": "air-jordan-1-retro-high-og-true-blue",
        "resellLinks": {
            "stockX": "https://stockx.com/air-jordan-1-retro-high-og-true-blue",
            "flightClub": "https://www.flightclub.com/air-jordan-1-retro-high-og-true-blue-dz5485-410",
            "goat": "http://www.goat.com/sneakers/air-jordan-1-retro-high-og-true-blue-dz5485-410"
        },
        "goatProductId": 1059448
    },
    {
        "lowestResellPrice": {
            "stockX": 203,
            "flightClub": 215,
            "goat": 215
        },
        "imageLinks": [],
        "_id": "63d09e90638bbe2c6be73cbb",
        "shoeName": "Jordan 11 Retro Cherry (2022)",
        "brand": "Jordan",
        "silhoutte": "Jordan 11 Retro",
        "styleID": "CT8012-116",
        "make": "Jordan 11 Retro",
        "colorway": "White/Varsity Red/Black",
        "retailPrice": 225,
        "thumbnail": "https://images.stockx.com/images/Air-Jordan-11-Retro-Cherry-2022-Product.jpg?fit=fill&bg=FFFFFF&w=700&h=500&fm=webp&auto=compress&trim=color&q=90&dpr=2&updated_at=1669100668",
        "releaseDate": "2022-12-10",
        "description": "A new entry in the lineage of the Air Jordan 11, the 'Cherry' also known as 'Varsity Red' features a clean 'colorway' that utilizes a Chicago Bulls inspired palette. The upper features white mesh with tonal webbing eyelets, while a shiny patent leather mudguard wraps around the entire shoe in a deep red hue. A red Jumpman logo appears on the back heel area, while a translucent rubber outsole finishes the look. A lightweight Phylon midsole provides cushioning while a carbon fiber spring plate offers structural support underfoot.",
        "urlKey": "air-jordan-11-retro-cherry-2022",
        "resellLinks": {
            "stockX": "https://stockx.com/air-jordan-11-retro-cherry-2022",
            "flightClub": "https://www.flightclub.com/air-jordan-11-retro-cherry-ct8012-116",
            "goat": "http://www.goat.com/sneakers/air-jordan-11-retro-cherry-ct8012-116"
        },
        "goatProductId": 920713
    },
    {
        "lowestResellPrice": {
            "stockX": 156,
            "flightClub": 135,
            "goat": 142
        },
        "imageLinks": [],
        "_id": "63d09e90638bbe2c6be73cbc",
        "shoeName": "Jordan 1 Low SE Concord",
        "brand": "Jordan",
        "silhoutte": "Jordan 1 Low SE",
        "styleID": "DV1309-100",
        "make": "Jordan 1 Low SE",
        "colorway": "White/Black",
        "retailPrice": 120,
        "thumbnail": "https://images.stockx.com/images/Air-Jordan-1-Low-SE-Concord.jpg?fit=fill&bg=FFFFFF&w=700&h=500&fm=webp&auto=compress&trim=color&q=90&dpr=2&updated_at=1672244358",
        "releaseDate": "2023-01-17",
        "description": "",
        "urlKey": "air-jordan-1-low-se-concord",
        "resellLinks": {
            "stockX": "https://stockx.com/air-jordan-1-low-se-concord",
            "flightClub": "https://www.flightclub.com/air-jordan-1-low-concord-dv1309-100",
            "goat": "http://www.goat.com/sneakers/air-jordan-1-low-concord-dv1309-100"
        },
        "goatProductId": 1107666
    },
    {
        "lowestResellPrice": {
            "stockX": 299,
            "flightClub": 292,
            "goat": 292
        },
        "imageLinks": [],
        "_id": "63d09e90638bbe2c6be73cbd",
        "shoeName": "Jordan 1 Retro High OG Chicago Lost and Found",
        "brand": "Jordan",
        "silhoutte": "Jordan 1 Retro High OG",
        "styleID": "DZ5485-612",
        "make": "Jordan 1 Retro High OG",
        "colorway": "Varsity Red/Black-Sail-Muslin",
        "retailPrice": 180,
        "thumbnail": "https://images.stockx.com/images/Air-Jordan-1-Retro-High-OG-Chicago-Reimagined-Product.jpg?fit=fill&bg=FFFFFF&w=700&h=500&fm=webp&auto=compress&trim=color&q=90&dpr=2&updated_at=1665691099",
        "releaseDate": "2022-11-19",
        "description": "The Air Jordan 1 Retro High OG 'Chicago Lost & Found' brings back the famous 'Chicago' 'colorway' with new storytelling elements. Featuring the OG high-cut shape, the leather upper features a white base with Varsity Red overlays and a black Swoosh and Wings logo. Cracked black leather on the padded collar gives it a vintage look, along with a pre-yellowed midsole. The packaging also tells the 'Lost & Found' story, with a damaged-looking box plastered with sale stickers showcasing a different colored lid. A receipt is also included, alluding to finding this vintage gem tucked away in an attic or storage space.",
        "urlKey": "air-jordan-1-retro-high-og-chicago-reimagined-lost-and-found",
        "resellLinks": {
            "stockX": "https://stockx.com/air-jordan-1-retro-high-og-chicago-reimagined-lost-and-found",
            "flightClub": "https://www.flightclub.com/air-jordan-1-retro-high-og-dz5485-612",
            "goat": "http://www.goat.com/sneakers/air-jordan-1-retro-high-og-dz5485-612"
        },
        "goatProductId": 920714
    },
    {
        "lowestResellPrice": {
            "stockX": 118,
            "flightClub": 117,
            "goat": 117
        },
        "imageLinks": [],
        "_id": "63d09e90638bbe2c6be73cbe",
        "shoeName": "Jordan 1 Low True Blue",
        "brand": "Jordan",
        "silhoutte": "Jordan 1 Low",
        "styleID": "553558-412",
        "make": "Jordan 1 Low",
        "colorway": "True Blue/Cement Grey/White",
        "retailPrice": 110,
        "thumbnail": "https://images.stockx.com/images/Air-Jordan-1-Low-True-Blue-Product.jpg?fit=fill&bg=FFFFFF&w=700&h=500&fm=webp&auto=compress&trim=color&q=90&dpr=2&updated_at=1674546559",
        "releaseDate": "2023-01-17",
        "description": "",
        "urlKey": "air-jordan-1-low-true-blue",
        "resellLinks": {
            "stockX": "https://stockx.com/air-jordan-1-low-true-blue",
            "flightClub": "https://www.flightclub.com/air-jordan-1-low-true-blue-cement-553558-412",
            "goat": "http://www.goat.com/sneakers/air-jordan-1-low-true-blue-cement-553558-412"
        },
        "goatProductId": 1096641
    },
    {
        "lowestResellPrice": {
            "stockX": 457,
            "flightClub": 485,
            "goat": 485
        },
        "imageLinks": [],
        "_id": "63d09e90638bbe2c6be73cbf",
        "shoeName": "Jordan 1 Retro Low OG SP Travis Scott Black Phantom",
        "brand": "Jordan",
        "silhoutte": "Jordan 1 Retro Low OG SP",
        "styleID": "DM7866-001",
        "make": "Jordan 1 Retro Low OG SP",
        "colorway": "Black/Phantom-Ale Brown-Racer Blue-Team Orange",
        "retailPrice": 150,
        "thumbnail": "https://images.stockx.com/images/Air-Jordan-1-Retro-Low-OG-SP-Travis-Scott-Black-Phantom-Product.jpg?fit=fill&bg=FFFFFF&w=700&h=500&fm=webp&auto=compress&trim=color&q=90&dpr=2&updated_at=1671732011",
        "releaseDate": "2022-12-15",
        "description": "The Travis Scott x Air Jordan 1 Low OG SP 'Black Phantom' sees the Houston-based rapper color up another AJ1 Low. This iteration features a blacked-out look, with nubuck and suede on the upper underscored by white contrast stitching throughout. Scott's signature reverse Swoosh remains, alongside a regular Swoosh on the medial side with Cactus Jack branding. The back heel features mismatched branding, with a Wings logo on the right shoe and a bee graphic on the left.",
        "urlKey": "air-jordan-1-retro-low-og-sp-travis-scott-black-phantom",
        "resellLinks": {
            "stockX": "https://stockx.com/air-jordan-1-retro-low-og-sp-travis-scott-black-phantom",
            "flightClub": "https://www.flightclub.com/travis-scott-x-air-jordan-1-low-og-sp-black-phantom-dm7866-001",
            "goat": "http://www.goat.com/sneakers/travis-scott-x-air-jordan-1-low-og-sp-black-phantom-dm7866-001"
        },
        "goatProductId": 1006990
    },
    {
        "lowestResellPrice": {
            "stockX": 234,
            "flightClub": 210,
            "goat": 210
        },
        "imageLinks": [],
        "_id": "63d09e90638bbe2c6be73cc0",
        "shoeName": "Jordan 11 Retro Cool Grey (2021)",
        "brand": "Jordan",
        "silhoutte": "Jordan 11 Retro",
        "styleID": "CT8012-005",
        "make": "Jordan 11 Retro",
        "colorway": "Medium Grey/Multi-Color/Multi-Color",
        "retailPrice": 225,
        "thumbnail": "https://images.stockx.com/images/Air-Jordan-11-Retro-Cool-Grey-2021-Product.jpg?fit=fill&bg=FFFFFF&w=700&h=500&fm=webp&auto=compress&trim=color&q=90&dpr=2&updated_at=1631898423",
        "releaseDate": "2021-12-11",
        "description": "Released in December 2021, the Air Jordan 11 Retro 'Cool Grey' 2021 brings back a 'colorway' from 2001 and 2010. Faithful to the OG, the shoe's upper is built with leather, finished in grey and supported by a darker grey patent leather mudguard. Tonal webbing eyelets are worked into the lacing system to secure the fit, while underfoot, a contrasting white phylon midsole houses full-length Air for cushioning, with a carbon fiber plate included for added support. An icy translucent rubber outsole provides traction.",
        "urlKey": "air-jordan-11-retro-cool-grey-2021",
        "resellLinks": {
            "stockX": "https://stockx.com/air-jordan-11-retro-cool-grey-2021",
            "flightClub": "https://www.flightclub.com/air-jordan-11-retro-cool-grey-2021-ct8012-005",
            "goat": "http://www.goat.com/sneakers/air-jordan-11-retro-cool-grey-2021-ct8012-005"
        },
        "goatProductId": 704157
    },
    {
        "lowestResellPrice": {
            "stockX": 174,
            "flightClub": 170,
            "goat": 170
        },
        "imageLinks": [],
        "_id": "63d09e90638bbe2c6be73cc1",
        "shoeName": "Jordan 12 Retro Black Taxi",
        "brand": "Jordan",
        "silhoutte": "Jordan 12 Retro",
        "styleID": "CT8013-071",
        "make": "Jordan 12 Retro",
        "colorway": "Black/Taxi",
        "retailPrice": 200,
        "thumbnail": "https://images.stockx.com/images/Air-Jordan-12-Retro-Black-Taxi-Product.jpg?fit=fill&bg=FFFFFF&w=700&h=500&fm=webp&auto=compress&trim=color&q=90&dpr=2&updated_at=1670484546",
        "releaseDate": "2022-12-03",
        "description": "Taking cues from the first release of the 'Taxi' AJ12, the Air Jordan 12 Retro 'Black Taxi' blacks out the championship silhouette in a stealthy makeover. Smooth black leather panels 'make' up the upper, paired with a black pebbled mudguard. A blacked out midsole and outsole continue the look, contrasted only by Taxi hits on the Jumpman and Two3 graphics on the tongue, eyelets and a molded panel on the side with 'Jumpman' branding. A small Taxi Jumpman logo peeks out from the outsole, where a carbon fiber plate is there for stability and Zoom Air units for cushioning.",
        "urlKey": "air-jordan-12-retro-black-taxi",
        "resellLinks": {
            "stockX": "https://stockx.com/air-jordan-12-retro-black-taxi",
            "flightClub": "https://www.flightclub.com/air-jordan-12-retro-black-taxi-ct8013-071",
            "goat": "http://www.goat.com/sneakers/air-jordan-12-retro-black-taxi-ct8013-071"
        },
        "goatProductId": 1024164
    },
    {
        "lowestResellPrice": {
            "stockX": 152,
            "flightClub": 148,
            "goat": 148
        },
        "imageLinks": [],
        "_id": "63d09e90638bbe2c6be73cc2",
        "shoeName": "Jordan 11 Retro Cherry (2022) (GS)",
        "brand": "Jordan",
        "silhoutte": "Jordan 11 Retro",
        "styleID": "378038-116",
        "make": "Jordan 11 Retro",
        "colorway": "White/Varsity Red-Black",
        "retailPrice": 185,
        "thumbnail": "https://images.stockx.com/images/Air-Jordan-11-Retro-Cherry-2022-GS-Product.jpg?fit=fill&bg=FFFFFF&w=700&h=500&fm=webp&auto=compress&trim=color&q=90&dpr=2&updated_at=1670397683",
        "releaseDate": "2022-12-10",
        "description": "Crafted for big kids, the Air Jordan 11 Retro GS 'Cherry' takes direct inspiration from a 2001 low-top. The AJ11 rides on a Phylon midsole in white with an interior Air-sole unit supported by a clear rubber outsole. A shiny patent leather mudguard in Varsity Red contrasts with the upper in white ballistic mesh and leather. Webbing eyelets secure white rope laces to lockdown the foot. Branding appears with '23' on the heel tab and the signature red Jumpman logo stitched on the collar.",
        "urlKey": "air-jordan-11-retro-cherry-2022-gs",
        "resellLinks": {
            "stockX": "https://stockx.com/air-jordan-11-retro-cherry-2022-gs",
            "flightClub": "https://www.flightclub.com/air-jordan-11-retro-gs-cherry-378038-116",
            "goat": "http://www.goat.com/sneakers/air-jordan-11-retro-gs-cherry-378038-116"
        },
        "goatProductId": 1085986
    },
    {
        "lowestResellPrice": {
            "stockX": 146,
            "flightClub": 159,
            "goat": 159
        },
        "imageLinks": [],
        "_id": "63d09e90638bbe2c6be73cc3",
        "shoeName": "Jordan 13 Retro Black University Blue",
        "brand": "Jordan",
        "silhoutte": "Jordan 13 Retro",
        "styleID": "DJ5982-041",
        "make": "Jordan 13 Retro",
        "colorway": "Black/University Blue/White",
        "retailPrice": 200,
        "thumbnail": "https://images.stockx.com/images/Air-Jordan-13-Retro-University-Blue-Product.jpg?fit=fill&bg=FFFFFF&w=700&h=500&fm=webp&auto=compress&trim=color&q=90&dpr=2&updated_at=1672642681",
        "releaseDate": "2022-12-23",
        "description": "Arriving in a familiar color palette but new for the AJ13, the Air Jordan 13 Retro 'Black University Blue' channels OG color blocking with classic colors. The upper features reflective black mesh overlays paired with black leather on the toe and tongue area, while rich University Blue suede wraps the back heel area and midsole. The black pods that represent a panther paw are also blacked out, leading to herringbone sections on the outsole. A carbon fiber adds stability underfoot, while Zoom Air units offer lightweight cushioning.",
        "urlKey": "air-jordan-13-retro-university-blue",
        "resellLinks": {
            "stockX": "https://stockx.com/air-jordan-13-retro-university-blue",
            "flightClub": "https://www.flightclub.com/air-jordan-13-retro-black-university-blue-dj5982-041",
            "goat": "http://www.goat.com/sneakers/air-jordan-13-retro-black-university-blue-dj5982-041"
        },
        "goatProductId": 1000360
    }
]
